pushsnapscript/__init__.py
pushsnapscript/artifacts.py
pushsnapscript/exceptions.py
pushsnapscript/script.py
pushsnapscript/snap_store.py
pushsnapscript/task.py
pushsnapscript/data/push_snap_task_schema.json
pushsnapscript/snapcraft/.flake8
pushsnapscript/snapcraft/.git
pushsnapscript/snapcraft/.gitignore
pushsnapscript/snapcraft/.gitmodules
pushsnapscript/snapcraft/.travis.yml
pushsnapscript/snapcraft/CODE_STYLE.md
pushsnapscript/snapcraft/CONTRIBUTING.md
pushsnapscript/snapcraft/COPYING
pushsnapscript/snapcraft/Dockerfile
pushsnapscript/snapcraft/HACKING.md
pushsnapscript/snapcraft/MANIFEST.in
pushsnapscript/snapcraft/README.md
pushsnapscript/snapcraft/TESTING.md
pushsnapscript/snapcraft/appveyor.yml
pushsnapscript/snapcraft/manual-tests.md
pushsnapscript/snapcraft/mypy.ini
pushsnapscript/snapcraft/pyproject.toml
pushsnapscript/snapcraft/requirements-devel.txt
pushsnapscript/snapcraft/requirements.txt
pushsnapscript/snapcraft/runtests.sh
pushsnapscript/snapcraft/setup.py
pushsnapscript/snapcraft/spread.yaml
pushsnapscript/snapcraft/units.py
pushsnapscript/snapcraft/.github/ISSUE_TEMPLATE.md
pushsnapscript/snapcraft/.github/PULL_REQUEST_TEMPLATE.md
pushsnapscript/snapcraft/.vscode/launch.json
pushsnapscript/snapcraft/bin/snapcraft
pushsnapscript/snapcraft/bin/snapcraftctl
pushsnapscript/snapcraft/debian/changelog
pushsnapscript/snapcraft/debian/compat
pushsnapscript/snapcraft/debian/control
pushsnapscript/snapcraft/debian/copyright
pushsnapscript/snapcraft/debian/rules
pushsnapscript/snapcraft/debian/snapcraft-completion
pushsnapscript/snapcraft/debian/snapcraft-examples.examples
pushsnapscript/snapcraft/debian/snapcraft-examples.lintian-overrides
pushsnapscript/snapcraft/debian/snapcraft-parser.install
pushsnapscript/snapcraft/debian/snapcraft-parser.lintian-overrides
pushsnapscript/snapcraft/debian/snapcraft.bash-completion
pushsnapscript/snapcraft/debian/snapcraft.install
pushsnapscript-1.0.0.dist-info/DESCRIPTION.rst
pushsnapscript-1.0.0.dist-info/METADATA
pushsnapscript-1.0.0.dist-info/RECORD
pushsnapscript-1.0.0.dist-info/WHEEL
pushsnapscript-1.0.0.dist-info/entry_points.txt
pushsnapscript-1.0.0.dist-info/metadata.json
pushsnapscript-1.0.0.dist-info/top_level.txt
