Metadata-Version: 2.0
Name: pushsnapscript
Version: 1.0.0
Summary: TaskCluster Ship-It Worker
Home-page: https://github.com/mozilla-releng/pushsnapscript
Author: Mozilla Release Engineering
Author-email: release+python@mozilla.com
License: MPL2
Platform: UNKNOWN
Classifier: Programming Language :: Python :: 3.6
Classifier: Programming Language :: Python :: 3.7
Requires-Dist: PyYAML (==3.13)
Requires-Dist: click (>=6.2)
Requires-Dist: mozilla-version
Requires-Dist: progressbar33 (==2.4)
Requires-Dist: pyelftools (==0.24)
Requires-Dist: pymacaroons (==0.9.2)
Requires-Dist: python-debian (==0.1.28)
Requires-Dist: pyxdg (==0.25)
Requires-Dist: requests-toolbelt (==0.6.0)
Requires-Dist: requests (<3,>=2)
Requires-Dist: requests-unixsocket (==0.1.5)
Requires-Dist: scriptworker
Requires-Dist: simplejson (==3.8.2)
Requires-Dist: tabulate (==0.7.5)
